tada_ai/__init__.py
tada_ai/client.py
tada_ai/exceptions.py
tada_ai/models/__init__.py
tada_ai/models/api_model.py
tada_ai/models/chunk_options.py
tada_ai/models/content_blocks.py
tada_ai/models/create_manual_space_input.py
tada_ai/models/langchain.py
tada_ai/models/reranker_options.py
tada_ai/models/search_query_input.py
tada_ai/models/search_record_chunk.py
tada_ai/models/search_result.py
tada_ai/models/space.py
tada_ai/models/space_file.py
tada_ai/models/space_files_list.py
tada_ai/models/space_list.py
tada_ai/py.typed
tada_ai/rest.py
tada_ai-0.4.0.dist-info/LICENSE
tada_ai-0.4.0.dist-info/METADATA
tada_ai-0.4.0.dist-info/WHEEL
tada_ai-0.4.0.dist-info/RECORD
