Metadata-Version: 2.1
Name: tada_ai
Version: 0.4.0
Summary: Tada AI API
Home-page: https://github.com/Tada-AI/python-client
License: MIT
Keywords: Tada AI API
Author: Tada AI
Author-email: suport@tadatoday.ai
Requires-Python: >=3.8,<4.0
Classifier: License :: OSI Approved :: MIT License
Classifier: Programming Language :: Python :: 3
Classifier: Programming Language :: Python :: 3.8
Classifier: Programming Language :: Python :: 3.9
Classifier: Programming Language :: Python :: 3.10
Classifier: Programming Language :: Python :: 3.11
Classifier: Programming Language :: Python :: 3.12
Requires-Dist: pydantic (>=2)
Requires-Dist: python-dateutil (>=2.8.2)
Requires-Dist: typing-extensions (>=4.7.1)
Requires-Dist: urllib3 (>=1.25.3)
Project-URL: Repository, https://github.com/Tada-AI/python-client
